nats_bench/__init__.py
nats_bench/api_size.py
nats_bench/api_topology.py
nats_bench/api_utils.py
nats_bench/genotype_utils.py
nats_bench-1.8.dist-info/LICENSE.md
nats_bench-1.8.dist-info/METADATA
nats_bench-1.8.dist-info/WHEEL
nats_bench-1.8.dist-info/top_level.txt
nats_bench-1.8.dist-info/RECORD
