Metadata-Version: 2.1
Name: nats-bench
Version: 1.8
Summary: API for NATS-Bench (a dataset/benchmark for neural architecture topology and size).
Home-page: https://github.com/D-X-Y/NATS-Bench
Author: Xuanyi Dong
Author-email: dongxuanyi888@gmail.com
License: MIT Licence
Keywords: NAS Dataset API DeepLearning
Platform: UNKNOWN
Classifier: Programming Language :: Python
Classifier: Programming Language :: Python :: 3
Classifier: Topic :: Database
Classifier: Topic :: Scientific/Engineering :: Artificial Intelligence
Classifier: License :: OSI Approved :: MIT License
Requires-Python: >=3.6
Requires-Dist: numpy (>=1.16.5)
